README.md
setup.cfg
setup.py
samsungtv/__init__.py
samsungtv/remote.py
samsungtv.egg-info/PKG-INFO
samsungtv.egg-info/SOURCES.txt
samsungtv.egg-info/dependency_links.txt
samsungtv.egg-info/requires.txt
samsungtv.egg-info/top_level.txt