Metadata-Version: 2.1
Name: samsungtv
Version: 1.0.0
Summary: Samsung Smart TV API wrapper
Home-page: https://github.com/vrachieru/samsung-tv-api
Author: Victor Rachieru
License: MIT
Platform: UNKNOWN
Classifier: Programming Language :: Python
Classifier: Programming Language :: Python :: 3
Classifier: Development Status :: 5 - Production/Stable
Classifier: Intended Audience :: Developers
Classifier: Intended Audience :: Education
Classifier: Intended Audience :: Information Technology
Classifier: Intended Audience :: Science/Research
Classifier: License :: OSI Approved :: MIT License
Requires-Python: >=3.0.0
